raiser.cp314t-win_amd64.pyd
cython_test_exception_raiser/__init__.py
cython_test_exception_raiser-25.11.1.dist-info/licenses/LICENSE
cython_test_exception_raiser-25.11.1.dist-info/METADATA
cython_test_exception_raiser-25.11.1.dist-info/WHEEL
cython_test_exception_raiser-25.11.1.dist-info/top_level.txt
cython_test_exception_raiser-25.11.1.dist-info/RECORD
