Metadata-Version: 2.4
Name: cython-test-exception-raiser
Version: 25.11.1
Summary: A trivial extension that just raises an exception.
Home-page: https://github.com/twisted/cython-test-exception-raiser
Author: Twisted Matrix Laboratories
Author-email: twisted-python@twistedmatrix.com
Maintainer: Thomas Grainger
Maintainer-email: cython-test-exception-raiser@graingert.co.uk
License: MIT
Classifier: Programming Language :: Python :: 3
Classifier: Programming Language :: Python :: 3 :: Only
Classifier: Programming Language :: Python :: 3.8
Classifier: Programming Language :: Python :: 3.9
Classifier: Programming Language :: Python :: 3.10
Classifier: Programming Language :: Python :: 3.11
Classifier: Programming Language :: Python :: 3.12
Classifier: Programming Language :: Python :: 3.13
Classifier: Programming Language :: Python :: 3.14
License-File: LICENSE
Dynamic: license-file
